{
  "date": "20260628",
  "updated": "2026-06-28",
  "source": "한국석유공사 오피넷",
  "oil": {
    "premium": {
      "price": 2423.19,
      "diff": -2.65
    },
    "gasoline": {
      "price": 1986.48,
      "diff": -9.62
    },
    "diesel": {
      "price": 1977.23,
      "diff": -9.95
    },
    "lpg": {
      "price": 1107.82,
      "diff": 0
    }
  },
  "sido": [
    {
      "name": "서울",
      "price": 2010.09,
      "diff": -7.92
    },
    {
      "name": "경기",
      "price": 1968.35,
      "diff": -12.16
    },
    {
      "name": "강원",
      "price": 1992.04,
      "diff": -6.07
    },
    {
      "name": "충북",
      "price": 1990.13,
      "diff": -7.01
    },
    {
      "name": "충남",
      "price": 1983.52,
      "diff": -8.3
    },
    {
      "name": "전북",
      "price": 1980.12,
      "diff": -8.2
    },
    {
      "name": "전남",
      "price": 1992.72,
      "diff": -8.18
    },
    {
      "name": "경북",
      "price": 1979.02,
      "diff": -8.63
    },
    {
      "name": "경남",
      "price": 1979.17,
      "diff": -7.05
    },
    {
      "name": "부산",
      "price": 1953.37,
      "diff": -12.01
    },
    {
      "name": "제주",
      "price": 2005.49,
      "diff": -9.01
    },
    {
      "name": "대구",
      "price": 1949.9,
      "diff": -14.88
    },
    {
      "name": "인천",
      "price": 1946.89,
      "diff": -23.01
    },
    {
      "name": "광주",
      "price": 1951.46,
      "diff": -14.21
    },
    {
      "name": "대전",
      "price": 1946.4,
      "diff": -19.12
    },
    {
      "name": "울산",
      "price": 1963.14,
      "diff": -10.37
    },
    {
      "name": "세종",
      "price": 1978.7,
      "diff": -9.19
    }
  ]
}
